{
  "created_at_utc": "2026-05-28T15:16:23.936065+00:00",
  "files_dir": "C:\\MT5PortableGoldMission\\MQL5\\Files",
  "reports": {
    "acceptance_report": "C:\\Users\\ZHAO ZHU INFORMATION\\Downloads\\algo-trading-system\\xau-usd\\xauusd-phase1\\outputs\\reports\\PHASE1_ACCEPTANCE_REPORT.md",
    "log_report": "C:\\Users\\ZHAO ZHU INFORMATION\\Downloads\\algo-trading-system\\xau-usd\\xauusd-phase1\\outputs\\reports\\PHASE1_DRY_RUN_LOG_REPORT.md",
    "runtime_health_report": "C:\\Users\\ZHAO ZHU INFORMATION\\Downloads\\algo-trading-system\\xau-usd\\xauusd-phase1\\outputs\\reports\\PHASE1_RUNTIME_HEALTH_REPORT.md",
    "soak_report": "C:\\Users\\ZHAO ZHU INFORMATION\\Downloads\\algo-trading-system\\xau-usd\\xauusd-phase1\\outputs\\reports\\PHASE1_SOAK_DRIFT_REPORT.md",
    "would_signal_report": "C:\\Users\\ZHAO ZHU INFORMATION\\Downloads\\algo-trading-system\\xau-usd\\xauusd-phase1\\outputs\\reports\\PHASE1_WOULD_SIGNAL_REPORT.md"
  },
  "runtime": {
    "decision_rows": 1065,
    "latest_row": {
      "bar_time": "2026.05.28 15:15:00",
      "block_reason": "phase1_dry_run_only",
      "br_direction": "SHORT",
      "br_stage": "WAIT_LEVEL_BREAK_RETEST",
      "br_would_signal": "false",
      "dry_run": "true",
      "risk_state": "NORMAL",
      "run_id": "phase1-dry-run-v0.7",
      "sbr_direction": "SHORT",
      "sbr_stage": "WAIT_LEVEL_BREAK_RETEST",
      "sbr_would_signal": "false",
      "server_time_status": "CLOCK_OK",
      "timestamp_broker": "2026.05.28 15:15:00",
      "timestamp_local": "2026.05.28 20:45:00",
      "trade_permission": "false"
    },
    "unique_run_ids": 6
  },
  "soak": {
    "active_market_streak_hours": 53.92,
    "code_freeze_hours": 28.58,
    "code_freeze_pass": false,
    "code_freeze_started_at": "2026-05-27T10:41:50Z",
    "current_streak_bar_count": 332,
    "current_streak_hours": 27.5,
    "last_restart_utc": "2026-05-27T10:41:55Z",
    "longest_streak_bar_count": 650,
    "longest_streak_hours": 53.92,
    "max_bar_gap_minutes": 15.0,
    "observed_days": 6.1771,
    "process_code_freeze_pass": false,
    "process_uptime_streak_hours": 28.57,
    "progress_pct": 100.0,
    "required_code_freeze_hours": 96.0,
    "required_days": 5,
    "required_uninterrupted_streak_hours": 72.0,
    "restart_count_during_current_streak": 0,
    "uninterrupted_soak_pass": false,
    "weekend_policy": "expected_market_breaks_pause_active_market_streak"
  },
  "status": {
    "acceptance": "PENDING",
    "log_verification": "PASS",
    "runtime_health": "PASS",
    "soak_analysis": "PASS",
    "would_signal": "PASS"
  },
  "would_signal": {
    "clusters": 118,
    "csv_path": "C:\\Users\\ZHAO ZHU INFORMATION\\Downloads\\algo-trading-system\\xau-usd\\xauusd-phase1\\outputs\\reports\\PHASE1_WOULD_SIGNAL_REVIEW.csv",
    "observer_conflicts": {
      "both_opposite_direction": 0,
      "both_same_direction": 52,
      "br_only": 14,
      "sbr_only": 0
    },
    "report_path": "C:\\Users\\ZHAO ZHU INFORMATION\\Downloads\\algo-trading-system\\xau-usd\\xauusd-phase1\\outputs\\reports\\PHASE1_WOULD_SIGNAL_REPORT.md",
    "rows": 118
  }
}